llmq/__init__.py
llmq/__main__.py
llmq/_version.py
llmq/cli/__init__.py
llmq/cli/main.py
llmq/cli/monitor.py
llmq/cli/receive.py
llmq/cli/submit.py
llmq/cli/worker.py
llmq/core/__init__.py
llmq/core/broker.py
llmq/core/config.py
llmq/core/models.py
llmq/core/pipeline.py
llmq/utils/__init__.py
llmq/utils/logging.py
llmq/utils/template.py
llmq/workers/__init__.py
llmq/workers/base.py
llmq/workers/dummy_worker.py
llmq/workers/semhash_worker.py
llmq/workers/vllm_worker.py
llmq-0.0.8.dist-info/METADATA
llmq-0.0.8.dist-info/WHEEL
llmq-0.0.8.dist-info/entry_points.txt
llmq-0.0.8.dist-info/top_level.txt
llmq-0.0.8.dist-info/RECORD
