Metadata-Version: 2.4
Name: llmq
Version: 0.0.8
Summary: todo
Author-email: Pieter <llmq@pieter.ai>
License: MIT
Project-URL: Homepage, https://github.com/ipieter/llmq
Project-URL: Repository, https://github.com/ipieter/llmq
Project-URL: Documentation, https://github.com/ipieter/llmq#readme
Project-URL: Issues, https://github.com/ipieter/llmq/issues
Keywords: llm,queue,vllm,gpu,inference,rabbitmq,async
Classifier: Development Status :: 3 - Alpha
Classifier: Intended Audience :: Developers
Classifier: License :: OSI Approved :: MIT License
Classifier: Programming Language :: Python :: 3
Classifier: Programming Language :: Python :: 3.9
Classifier: Programming Language :: Python :: 3.10
Classifier: Programming Language :: Python :: 3.11
Classifier: Programming Language :: Python :: 3.12
Requires-Python: >=3.9
Requires-Dist: vllm>=0.7.0
Requires-Dist: transformers>=4.47.0
Requires-Dist: datasets>=4.0.0
Requires-Dist: aio-pika>=9.5.0
Requires-Dist: click>=8.1.7
Requires-Dist: pydantic>=2.10.0
Requires-Dist: rich>=13.9.0
Requires-Dist: python-dotenv>=1.0.1
Requires-Dist: httpx>=0.27.0
Requires-Dist: PyYAML>=6.0.0
Requires-Dist: semhash>=0.3.1
Provides-Extra: test
Requires-Dist: pytest>=8.0.0; extra == "test"
Requires-Dist: pytest-asyncio>=0.23.0; extra == "test"
Requires-Dist: pytest-mock>=3.12.0; extra == "test"
Requires-Dist: pytest-cov>=6.0.0; extra == "test"
Requires-Dist: faker>=30.0.0; extra == "test"
Requires-Dist: types-PyYAML>=6.0.0; extra == "test"
Requires-Dist: black>=24.0.0; extra == "test"
Requires-Dist: ruff>=0.8.0; extra == "test"
Requires-Dist: mypy>=1.13.0; extra == "test"
Provides-Extra: dev
Requires-Dist: llmq[test]; extra == "dev"
Requires-Dist: bandit[toml]>=1.7.0; extra == "dev"
Requires-Dist: safety>=3.0.0; extra == "dev"
Requires-Dist: build>=1.0.0; extra == "dev"
Requires-Dist: twine>=4.0.0; extra == "dev"
Requires-Dist: setuptools-scm[toml]>=6.2; extra == "dev"
Requires-Dist: pre-commit>=4.3.0; extra == "dev"
